{
  "contacts": [
    {
      "id": "fe797bc1-7edc-4954-b6da-494d27413100",
      "name": "addwithcontextapieditt",
      "email": "awcapi@yahoo.com"
    },
    {
      "id": "c11ab0db-661f-453f-8ff8-aa1fff81a57d",
      "name": "trypopupeditt",
      "email": "trypopup@yahoo.ced"
    },
    {
      "id": "20b099b5-dd72-4094-8fcb-b21bb8fc9f34",
      "name": "addcontact again",
      "email": "addcontactpopup@gmail.com"
    },
    {
      "id": "824e5a67-9a99-45b0-9bd7-34266afab992",
      "name": "tryaddnew",
      "email": "tryy@gmai.de"
    }
  ]
}